README.md
setup.py
tacPy/__init__.py
tacPy/full_tac_api_help.txt.example
tacPy.egg-info/PKG-INFO
tacPy.egg-info/SOURCES.txt
tacPy.egg-info/dependency_links.txt
tacPy.egg-info/requires.txt
tacPy.egg-info/top_level.txt