Metadata-Version: 1.0
Name: tacPy
Version: 0.1
Summary: A library for working with the Talend Administration Center API
Home-page: https://github.com/jgillmanjr/tacPy
Author: Jason Gillman Jr.
Author-email: jason@rrfaae.com
License: UNKNOWN
Platform: UNKNOWN
